{
  "swagger": "2.0",
  "info": {
    "title": "user.proto",
    "version": "version not set"
  },
  "tags": [
    {
      "name": "UserService"
    }
  ],
  "consumes": [
    "application/json"
  ],
  "produces": [
    "application/json"
  ],
  "paths": {},
  "definitions": {
    "protobufAny": {
      "type": "object",
      "properties": {
        "@type": {
          "type": "string"
        }
      },
      "additionalProperties": {}
    },
    "rpcStatus": {
      "type": "object",
      "properties": {
        "code": {
          "type": "integer",
          "format": "int32"
        },
        "message": {
          "type": "string"
        },
        "details": {
          "type": "array",
          "items": {
            "$ref": "#/definitions/protobufAny"
          }
        }
      }
    },
    "v1ListUserReply": {
      "type": "object",
      "properties": {
        "items": {
          "type": "array",
          "items": {
            "$ref": "#/definitions/v1User"
          }
        },
        "total": {
          "type": "integer",
          "format": "int32"
        }
      }
    },
    "v1User": {
      "type": "object",
      "properties": {
        "id": {
          "type": "string",
          "format": "uint64"
        },
        "user_name": {
          "type": "string"
        },
        "password": {
          "type": "string"
        },
        "nick_name": {
          "type": "string"
        },
        "email": {
          "type": "string"
        },
        "roles": {
          "type": "array",
          "items": {
            "type": "string"
          }
        },
        "token": {
          "type": "string"
        }
      }
    }
  }
}
